[
    {
        "id": "1",
        "name": "Omar Emad",
        "package": "Cash",
        "orders": "12",
        "address":"Zahraa El Maadi",
        "number":"01111204333",
        "date": "1-1-2019"
    },
       {
        "id": "2",
        "name": "Tarek Tolba",
        "package": "Neat",
        "orders": "19",
        "address":"Sheraton",
        "number":"01246313433",
        "date": "12-2-2019"
    },
        {
        "id": "3",
        "name": "Belal Tarek",
        "package": "Neat",
        "orders": "2",
        "address":"Madinet Nasr",
        "number":"01212312333",
        "date": "15-2-2019"
    },
        {
        "id": "4",
        "name": "Osama",
        "package": "Cash",
        "orders": "0",
        "address":"Madinet Nasr",
        "number":"01556604333",
        "date": "12-2-2019"
    },
        {
        "id": "5",
        "name": "Nada Saaeed",
        "package": "Pretty Neat",
        "orders": "19",
        "address":"Helwan",
        "number":"01252322333",
        "date": "1-1-2019"
    },
    {
        "id": "6",
        "name": "Mahitab Dagher",
        "package": "Pretty Neat",
        "orders": "87",
        "address":"Helwan",
        "number":"01124422555",
        "date": "1-5-2019"
    }
]
